fastapi_sqla/__init__.py
fastapi_sqla/_pytest_plugin.py
fastapi_sqla/async_pagination.py
fastapi_sqla/async_sqla.py
fastapi_sqla/aws_aurora_support.py
fastapi_sqla/aws_rds_iam_support.py
fastapi_sqla/base.py
fastapi_sqla/models.py
fastapi_sqla/pagination.py
fastapi_sqla/py.typed
fastapi_sqla/sqla.py
fastapi_sqla-3.5.11.dist-info/LICENSE
fastapi_sqla-3.5.11.dist-info/METADATA
fastapi_sqla-3.5.11.dist-info/WHEEL
fastapi_sqla-3.5.11.dist-info/entry_points.txt
fastapi_sqla-3.5.11.dist-info/RECORD
