Metadata-Version: 2.1
Name: fastapi-sqla
Version: 3.5.11
Summary: SQLAlchemy extension for FastAPI with support for pagination, asyncio, SQLModel, and pytest, ready for production.
Home-page: https://github.com/dialoguemd/fastapi-sqla
License: MIT
Keywords: FastAPI,SQLAlchemy,asyncio,pytest,alembic
Author: Hadrien David
Author-email: hadrien.david@dialogue.co
Requires-Python: >=3.9,<3.14
Classifier: Development Status :: 5 - Production/Stable
Classifier: Environment :: Web Environment
Classifier: Framework :: AsyncIO
Classifier: Framework :: FastAPI
Classifier: Intended Audience :: Developers
Classifier: Intended Audience :: Information Technology
Classifier: Intended Audience :: System Administrators
Classifier: License :: OSI Approved :: MIT License
Classifier: Operating System :: OS Independent
Classifier: Programming Language :: Python
Classifier: Programming Language :: Python :: 3
Classifier: Programming Language :: Python :: 3.9
Classifier: Programming Language :: Python :: 3.10
Classifier: Programming Language :: Python :: 3.11
Classifier: Programming Language :: Python :: 3.12
Classifier: Programming Language :: Python :: 3.13
Classifier: Programming Language :: Python :: 3 :: Only
Classifier: Programming Language :: SQL
Classifier: Topic :: Internet
Classifier: Topic :: Internet :: WWW/HTTP
Classifier: Topic :: Internet :: WWW/HTTP :: HTTP Servers
Classifier: Topic :: Software Development
Classifier: Topic :: Software Development :: Libraries
Classifier: Topic :: Software Development :: Libraries :: Application Frameworks
Classifier: Topic :: Software Development :: Libraries :: Python Modules
Classifier: Typing :: Typed
Provides-Extra: asyncpg
Provides-Extra: aws-rds-iam
Provides-Extra: psycopg2
Provides-Extra: pytest-plugin
Provides-Extra: sqlmodel
Requires-Dist: alembic (>=1.4.3,<2) ; extra == "pytest-plugin"
Requires-Dist: asyncpg (>=0.28.0,<0.32.0) ; extra == "asyncpg"
Requires-Dist: boto3 (>=1.24.74,<2) ; extra == "aws-rds-iam"
Requires-Dist: deprecated (>=1.2,<2)
Requires-Dist: fastapi (>=0.95.1,<0.126)
Requires-Dist: psycopg2 (>=2.8.6,<3) ; extra == "psycopg2"
Requires-Dist: pydantic (>=1,<3)
Requires-Dist: sqlalchemy (>=1.3,<3)
Requires-Dist: sqlmodel (>=0.0.14,<0.0.28) ; extra == "sqlmodel"
Requires-Dist: structlog (>=20,<26)
Project-URL: Repository, https://github.com/dialoguemd/fastapi-sqla
